README.md
pyproject.toml
segmentedstring/__init__.py
segmentedstring/segmented_string.py
segmentedstring.egg-info/PKG-INFO
segmentedstring.egg-info/SOURCES.txt
segmentedstring.egg-info/dependency_links.txt
segmentedstring.egg-info/top_level.txt
tests/test_segmented_string.py